README.md
setup.py
cvnet/__init__.py
cvnet/figure.py
cvnet.egg-info/PKG-INFO
cvnet.egg-info/SOURCES.txt
cvnet.egg-info/dependency_links.txt
cvnet.egg-info/not-zip-safe
cvnet.egg-info/requires.txt
cvnet.egg-info/top_level.txt
cvnet/../LICENSE
cvnet/../README.md
cvnet/../requirements.txt
cvnet/configs/__init__.py
cvnet/configs/defaults.py
cvnet/dataset/__init__.py
cvnet/dataset/augmentations.py
cvnet/dataset/cifar.py
cvnet/dataset/cityscapes_dataset.py
cvnet/dataset/classy_cifar.py
cvnet/dataset/classy_dataset.py
cvnet/dataset/fashion_mnist.py
cvnet/dataset/image_augmentation.py
cvnet/dataset/image_path_dataset.py
cvnet/dataset/list_dataset.py
cvnet/dataset/mnist.py
cvnet/dataset/pascalvoc_dataset.py
cvnet/dataset/transform.py
cvnet/dataset/det/__init__.py
cvnet/dataset/det/coco_det_generator.py
cvnet/dataset/det/voc_det_generator.py
cvnet/engine/__init__.py
cvnet/engine/inference.py
cvnet/engine/loss.py
cvnet/engine/metrics.py
cvnet/engine/optimizers.py
cvnet/engine/schedulers.py
cvnet/engine/trainer.py
cvnet/models/__init__.py
cvnet/models/cls/__init__.py
cvnet/models/cls/alexnet.py
cvnet/models/cls/custom_layer.py
cvnet/models/cls/densenet.py
cvnet/models/cls/googlenet.py
cvnet/models/cls/lenet.py
cvnet/models/cls/nin.py
cvnet/models/cls/resnet.py
cvnet/models/cls/resnet_main.py
cvnet/models/cls/resnet_model.py
cvnet/models/cls/vgg.py
cvnet/models/det/__init__.py
cvnet/models/gan/__init__.py
cvnet/models/gan/gan.py
cvnet/models/gan/gan_lightning.py
cvnet/models/image_captioning/__init__.py
cvnet/models/image_captioning/build_vocab.py
cvnet/models/image_captioning/data_loader.py
cvnet/models/image_captioning/model.py
cvnet/models/image_captioning/resize.py
cvnet/models/image_captioning/sample.py
cvnet/models/image_captioning/train.py
cvnet/models/ocr/__init__.py
cvnet/models/ocr/create_imdb_dataset.py
cvnet/models/ocr/dataset.py
cvnet/models/ocr/demo.py
cvnet/models/ocr/model.py
cvnet/models/ocr/test.py
cvnet/models/ocr/train.py
cvnet/models/ocr/utils.py
cvnet/models/ocr/layers/__init__.py
cvnet/models/ocr/layers/attn.py
cvnet/models/ocr/layers/bilstm.py
cvnet/models/ocr/layers/feature_extraction.py
