Metadata-Version: 2.1
Name: cvnet
Version: 0.1.1
Summary: Fast Use Computer Vision Tools
Home-page: https://github.com/shibing624/cvnet
Author: XuMing
Author-email: xuming624@qq.com
License: Apache 2.0
Keywords: Computer Vision,CV,image_classification,object_detection,gan,ocr,vae,cls,style_transfer
Platform: Windows
Platform: Linux
Platform: Solaris
Platform: Mac OS-X
Platform: Unix
Classifier: Intended Audience :: Developers
Classifier: Operating System :: OS Independent
Classifier: Natural Language :: Chinese (Simplified)
Classifier: Natural Language :: Chinese (Traditional)
Classifier: Programming Language :: Python
Classifier: Programming Language :: Python :: 3
Classifier: Programming Language :: Python :: 3.6
Classifier: Programming Language :: Python :: 3.7
Classifier: Programming Language :: Python :: 3.8
Classifier: Topic :: Text Processing :: Linguistic
Classifier: Topic :: Scientific/Engineering :: Artificial Intelligence
Requires-Python: >=3.6.0
